semgrep_mcp/__init__.py
semgrep_mcp/__main__.py
semgrep_mcp/server.py
mseep_semgrep_mcp-0.2.2.dist-info/METADATA
mseep_semgrep_mcp-0.2.2.dist-info/WHEEL
mseep_semgrep_mcp-0.2.2.dist-info/entry_points.txt
mseep_semgrep_mcp-0.2.2.dist-info/licenses/LICENSE
mseep_semgrep_mcp-0.2.2.dist-info/RECORD
